cmislib/__init__.py
cmislib/cmis_services.py
cmislib/domain.py
cmislib/exceptions.py
cmislib/messages.py
cmislib/model.py
cmislib/util.py
cmislib/atompub/__init__.py
cmislib/atompub/binding.py
cmislib/browser/__init__.py
cmislib/browser/binding.py
cmislib-0.7.0.dist-info/LICENSE.txt
cmislib-0.7.0.dist-info/METADATA
cmislib-0.7.0.dist-info/NOTICE.txt
cmislib-0.7.0.dist-info/WHEEL
cmislib-0.7.0.dist-info/top_level.txt
cmislib-0.7.0.dist-info/RECORD
