Metadata-Version: 2.1
Name: cmislib
Version: 0.7.0
Summary: Apache Chemistry CMIS client library for Python
Home-page: http://chemistry.apache.org/
Author: Apache Chemistry Project
Author-email: dev@chemistry.apache.org
License: Apache License (2.0)
Classifier: Development Status :: 4 - Beta
Classifier: Intended Audience :: Developers
Classifier: License :: OSI Approved :: Apache Software License
Classifier: Operating System :: OS Independent
Classifier: Programming Language :: Python :: 2.7
Classifier: Programming Language :: Python :: 3.4
Classifier: Programming Language :: Python :: 3.5
Classifier: Programming Language :: Python :: 3.6
Classifier: Topic :: Software Development :: Libraries
License-File: LICENSE.txt
License-File: NOTICE.txt
Requires-Dist: iso8601
Requires-Dist: requests
Requires-Dist: requests-toolbelt
